html4quiz/__init__.py
html4quiz/_common.py
html4quiz/_generateEm.py
html4quiz/_scoreEm.py
html4quiz/makeChoices.py
html4quiz-0.0.46.dist-info/METADATA
html4quiz-0.0.46.dist-info/WHEEL
html4quiz-0.0.46.dist-info/licenses/LICENSE.txt
html4quiz-0.0.46.dist-info/RECORD
